staran/__init__.py
staran/date/__init__.py
staran/date/core/__init__.py
staran/date/core/core.py
staran/date/core/i18n.py
staran/date/core/lunar.py
staran/date/examples/__init__.py
staran/date/examples/basic_usage.py
staran/date/examples/enhanced_features.py
staran/date/examples/v1010_features_demo.py
staran/date/examples/v108_features_demo.py
staran/date/examples/v109_features_demo.py
staran/date/extensions/__init__.py
staran/date/extensions/expressions.py
staran/date/extensions/solar_terms.py
staran/date/extensions/timezone.py
staran/date/integrations/__init__.py
staran/date/integrations/api_server.py
staran/date/integrations/visualization.py
staran/date/tests/__init__.py
staran/date/tests/run_tests.py
staran/date/tests/test_core.py
staran/date/tests/test_enhancements.py
staran/date/tests/test_v1010_features.py
staran/date/tests/test_v108_features.py
staran/date/tests/test_v109_features.py
staran/date/utils/__init__.py
staran/date/utils/helpers.py
staran-1.0.11.dist-info/licenses/LICENSE
staran-1.0.11.dist-info/METADATA
staran-1.0.11.dist-info/WHEEL
staran-1.0.11.dist-info/entry_points.txt
staran-1.0.11.dist-info/top_level.txt
staran-1.0.11.dist-info/RECORD
