Metadata-Version: 2.4
Name: staran
Version: 1.0.11
Summary: staran - 企业级Python日期处理库
Home-page: https://github.com/starlxa/staran
Author: StarAn
Author-email: starlxa@icloud.com
License: MIT
Project-URL: Bug Reports, https://github.com/starlxa/staran/issues
Project-URL: Source, https://github.com/starlxa/staran
Project-URL: Documentation, https://github.com/starlxa/staran/blob/master/API_REFERENCE.md
Keywords: date datetime utilities time-processing lunar calendar i18n timezone visualization api
Classifier: Development Status :: 5 - Production/Stable
Classifier: Intended Audience :: Developers
Classifier: Topic :: Software Development :: Libraries :: Python Modules
Classifier: Topic :: Utilities
Classifier: Topic :: Software Development :: Localization
Classifier: Topic :: Scientific/Engineering :: Visualization
Classifier: Programming Language :: Python :: 3
Classifier: Programming Language :: Python :: 3.7
Classifier: Programming Language :: Python :: 3.8
Classifier: Programming Language :: Python :: 3.9
Classifier: Programming Language :: Python :: 3.10
Classifier: Programming Language :: Python :: 3.11
Classifier: Programming Language :: Python :: 3.12
Classifier: Operating System :: OS Independent
Classifier: License :: OSI Approved :: MIT License
Requires-Python: >=3.7
License-File: LICENSE
Provides-Extra: visualization
Requires-Dist: matplotlib>=3.0.0; extra == "visualization"
Requires-Dist: plotly>=5.0.0; extra == "visualization"
Provides-Extra: web
Requires-Dist: flask>=2.0.0; extra == "web"
Provides-Extra: full
Requires-Dist: matplotlib>=3.0.0; extra == "full"
Requires-Dist: plotly>=5.0.0; extra == "full"
Requires-Dist: flask>=2.0.0; extra == "full"
Provides-Extra: dev
Requires-Dist: pytest>=6.0.0; extra == "dev"
Requires-Dist: pytest-cov>=2.0.0; extra == "dev"
Requires-Dist: black>=21.0.0; extra == "dev"
Requires-Dist: flake8>=3.8.0; extra == "dev"
Requires-Dist: mypy>=0.800; extra == "dev"
Dynamic: author
Dynamic: author-email
Dynamic: classifier
Dynamic: description
Dynamic: description-content-type
Dynamic: home-page
Dynamic: keywords
Dynamic: license
Dynamic: license-file
Dynamic: project-url
Dynamic: provides-extra
Dynamic: requires-python
Dynamic: summary
